LICENSE
MANIFEST.in
README.rst
requirements.txt
setup.py
pwed/__init__.py
pwed/__main__.py
pwed/bibtex.py
pwed/constants.py
pwed/objects.py
pwed/utils.py
pwed/convert/__init__.py
pwed/convert/utilities.py
pwed/protocols/__init__.py
pwed/protocols/protocol_base.py
pwed/protocols/protocol_import_diffraction_images.py
pwed/tests/__init__.py
pwed/tests/__main__.py
pwed/tests/test_ed_base.py
pwed/viewers/__init__.py
pwed/viewers/viewers_data.py
scipion_ed.egg-info/PKG-INFO
scipion_ed.egg-info/SOURCES.txt
scipion_ed.egg-info/dependency_links.txt
scipion_ed.egg-info/entry_points.txt
scipion_ed.egg-info/requires.txt
scipion_ed.egg-info/top_level.txt