Metadata-Version: 2.1
Name: scipion-ed
Version: 3!1.0.0
Summary: Base pyworkflow plugin for Electron Diffraction image processing
Home-page: https://github.com/scipion-ed/scipion-ed
Author: J.M. De la Rosa Trevin, Viktor E. G. Bengtsson
Author-email: delarosatrevin@scilifelab.se, viktor.bengtsson@mmk.su.se
License: UNKNOWN
Project-URL: Bug Reports, https://github.com/scipion-ed/scipion-ed/issues
Project-URL: Source, https://github.com/scipion-ed/scipion-ed/
Keywords: workflows science pyworkflow image-processing scipion electron diffraction
Platform: UNKNOWN
Classifier: Development Status :: 5 - Production/Stable
Classifier: Intended Audience :: Science/Research
Classifier: License :: OSI Approved :: GNU General Public License v3 (GPLv3)
Classifier: Programming Language :: Python :: 3.6
Classifier: Programming Language :: Python :: 3.7
Classifier: Programming Language :: Python :: 3.8
Classifier: Programming Language :: Python :: 3 :: Only
Classifier: Topic :: Scientific/Engineering
License-File: LICENSE
